grz_db/__init__.py
grz_db/common.py
grz_db/errors.py
grz_db/py.typed
grz_db/migrations/README.md
grz_db/migrations/env.py
grz_db/migrations/script.py.mako
grz_db/migrations/versions/1a9bd994df1b_initial.py
grz_db/migrations/versions/9bf36a91c87e_add_reporting_columns.py
grz_db/migrations/versions/fb3df229a77b_initial_quartalsbericht_support.py
grz_db/models/__init__.py
grz_db/models/author.py
grz_db/models/base.py
grz_db/models/submission.py
grz_db-1.2.0.dist-info/METADATA
grz_db-1.2.0.dist-info/WHEEL
grz_db-1.2.0.dist-info/licenses/LICENSE
grz_db-1.2.0.dist-info/RECORD
